LICENSE
MANIFEST.in
README.rst
setup.cfg
setup.py
pesky/__init__.py
pesky/defaults/__init__.py
pesky/defaults/defaults.py
pesky/defaults/distcmd.py
pesky/defaults/errors.py
pesky/defaults/package.py
pesky/defaults/system.py
pesky/defaults/version.py
pesky_defaults.egg-info/PKG-INFO
pesky_defaults.egg-info/SOURCES.txt
pesky_defaults.egg-info/dependency_links.txt
pesky_defaults.egg-info/entry_points.txt
pesky_defaults.egg-info/namespace_packages.txt
pesky_defaults.egg-info/top_level.txt