Metadata-Version: 1.0
Name: pesky-defaults
Version: 0.0.2
Summary: Pesky configuration defaults interface
Home-page: https://github.com/msfrank/pesky-defaults
Author: Michael Frank
Author-email: syntaxockey@gmail.com
License: UNKNOWN
Platform: UNKNOWN
Classifier: Development Status :: 3 - Alpha
Classifier: Intended Audience :: Developers
Classifier: License :: OSI Approved :: BSD License
Classifier: Natural Language :: English
Classifier: Programming Language :: Python :: 2
